memalloy-0.1.0.dist-info/METADATA
memalloy-0.1.0.dist-info/WHEEL
memalloy-0.1.0.dist-info/licenses/LICENSE-APACHE
memalloy-0.1.0.dist-info/licenses/LICENSE-MIT
memalloy/__init__.py
memalloy/__main__.py
memalloy/_memalloy.cp313-win_amd64.pyd
memalloy-0.1.0.dist-info/RECORD
